<?xml version="1.0"?>
<lesQcm>
    <qcm idQcm="1">
        <nomQcm>un nom</nomQcm>
        <typeDeCours>5</typeDeCours>
        <pseudo>NicolasM</pseudo>
        <lesQuestions>
            <question num="1">
                <libele>Est-ce que t'es chaud ? Pour le projet ???</libele>
                <lesReponses>
                    <reponse idReponse="1" value="true">Oui</reponse>
                    <reponse idReponse="2" value="false">Non</reponse>
                </lesReponses>
            </question>
            <question num="2">
                <libele>We are going to succeed ???</libele>
                <lesReponses>
                    <reponse idReponse="1" value="false">No im not good!</reponse>
                    <reponse idReponse="2" value="true">Of course we are the best</reponse>
                </lesReponses>
            </question>
        </lesQuestions>
    </qcm>
</lesQcm>